{
  "sections": {
    "homepage-header": {
      "type": "homepage-header",
      "settings": {
      }
    },
    "home-about": {
      "type": "home-about",
      "settings": {
        "about-info-new": "<h1>About the <a href=\"https:\/\/www.namknights.org\/default.aspx\" target=\"_blank\" title=\"https:\/\/www.namknights.org\/default.aspx\">Nam Knights MC<\/a> <\/h1><p>Our mission is to honor the memory of American Veterans and Police Officers who have lost their lives in the line of duty, to assist Veterans and Police Officers in their time of need and to promote community awareness through sponsorship and participation in various fundraising events. There are 78 Chapters throughout the US and Canada.<\/p><p>The Nam Knights Motorcycle Club continues to grow and thrive today due to the extraordinary dedication of its members, their families and our benevolent supporters.<\/p>"
      }
    },
    "homepage-tiles": {
      "type": "homepage-collection-tiles",
      "settings": {
      }
    },
    "74cb6d1d-de7d-41a2-befe-9a6a8cbbf241": {
      "type": "featured-product",
      "blocks": {
        "template--16923250950403__74cb6d1d-de7d-41a2-befe-9a6a8cbbf241-text-1": {
          "type": "text",
          "settings": {
            "text": "{{ section.settings.product.vendor }}",
            "text_style": "uppercase"
          }
        },
        "template--16923250950403__74cb6d1d-de7d-41a2-befe-9a6a8cbbf241-title-1": {
          "type": "title",
          "settings": {
            "heading_size": "h1"
          }
        },
        "template--16923250950403__74cb6d1d-de7d-41a2-befe-9a6a8cbbf241-price-1": {
          "type": "price",
          "settings": {
          }
        },
        "template--16923250950403__74cb6d1d-de7d-41a2-befe-9a6a8cbbf241-variant_picker-1": {
          "type": "variant_picker",
          "settings": {
            "picker_type": "button"
          }
        },
        "template--16923250950403__74cb6d1d-de7d-41a2-befe-9a6a8cbbf241-quantity_selector-1": {
          "type": "quantity_selector",
          "settings": {
          }
        },
        "template--16923250950403__74cb6d1d-de7d-41a2-befe-9a6a8cbbf241-buy_buttons-1": {
          "type": "buy_buttons",
          "settings": {
            "show_dynamic_checkout": true,
            "show_gift_card_recipient": true
          }
        },
        "template--16923250950403__74cb6d1d-de7d-41a2-befe-9a6a8cbbf241-share-1": {
          "type": "share",
          "settings": {
            "share_label": "Share"
          }
        }
      },
      "block_order": [
        "template--16923250950403__74cb6d1d-de7d-41a2-befe-9a6a8cbbf241-text-1",
        "template--16923250950403__74cb6d1d-de7d-41a2-befe-9a6a8cbbf241-title-1",
        "template--16923250950403__74cb6d1d-de7d-41a2-befe-9a6a8cbbf241-price-1",
        "template--16923250950403__74cb6d1d-de7d-41a2-befe-9a6a8cbbf241-variant_picker-1",
        "template--16923250950403__74cb6d1d-de7d-41a2-befe-9a6a8cbbf241-quantity_selector-1",
        "template--16923250950403__74cb6d1d-de7d-41a2-befe-9a6a8cbbf241-buy_buttons-1",
        "template--16923250950403__74cb6d1d-de7d-41a2-befe-9a6a8cbbf241-share-1"
      ],
      "settings": {
        "product": "black-long-sleeve-ribbon-t",
        "color_scheme": "",
        "secondary_background": false,
        "media_size": "medium",
        "constrain_to_viewport": true,
        "media_fit": "contain",
        "media_position": "left",
        "image_zoom": "lightbox",
        "hide_variants": false,
        "enable_video_looping": false,
        "padding_top": 36,
        "padding_bottom": 36
      }
    }
  },
  "order": [
    "homepage-header",
    "home-about",
    "homepage-tiles",
    "74cb6d1d-de7d-41a2-befe-9a6a8cbbf241"
  ]
}